kintomo/__init__.py
kintomo/_typing.py
kintomo/ktm.py
kintomo/py.typed
kintomo-0.1.0.dist-info/WHEEL
kintomo-0.1.0.dist-info/METADATA
kintomo-0.1.0.dist-info/RECORD
