Metadata-Version: 2.3
Name: kintomo
Version: 0.1.0
Summary: Python library to create optically thick kinematic toy models and explore their kinematics, given a user-defined structure and velocity, projected on a grid.
Author: gwf
Author-email: gwf <ysengrin9@gmail.com>
Requires-Dist: astropy>=7.2.0
Requires-Dist: gpgi>=2.1.0
Requires-Dist: jupyter>=1.1.1
Requires-Dist: matplotlib>=3.10.8
Requires-Dist: nonos>=0.19.1
Requires-Dist: numpy>=2.3.5
Requires-Dist: scikit-image>=0.25.2
Requires-Python: >=3.13
